prysm/__init__.py
prysm/_phase.py
prysm/_richdata.py
prysm/conf.py
prysm/convolution.py
prysm/coordinates.py
prysm/degredations.py
prysm/detector.py
prysm/fttools.py
prysm/geometry.py
prysm/gerchberg.py
prysm/interferogram.py
prysm/io.py
prysm/jacobi.py
prysm/mathops.py
prysm/mtf_utils.py
prysm/objects.py
prysm/otf.py
prysm/plotting.py
prysm/propagation.py
prysm/psf.py
prysm/pupil.py
prysm/qpoly.py
prysm/refractive.py
prysm/sample_data.py
prysm/thinfilm.py
prysm/thinlens.py
prysm/util.py
prysm/wavelengths.py
prysm/zernike.py
prysm-0.19.1.dist-info/LICENSE.md
prysm-0.19.1.dist-info/METADATA
prysm-0.19.1.dist-info/WHEEL
prysm-0.19.1.dist-info/top_level.txt
prysm-0.19.1.dist-info/zip-safe
prysm-0.19.1.dist-info/RECORD
