Metadata-Version: 2.1
Name: prysm
Version: 0.19.1
Summary: a python optics module
Home-page: http://prysm.readthedocs.io
Author: Brandon Dube
Author-email: brandon@retrorefractions.com
License: MIT
Keywords: optics,wavefront,numerical propagation,geometrical optics,psf,mtf,interferogram,pupil,aberration,imaging,simulation,slanted-edge
Platform: any
Classifier: Development Status :: 4 - Beta
Classifier: Intended Audience :: Science/Research
Classifier: License :: OSI Approved :: MIT License
Classifier: Programming Language :: Python :: 3.6
Classifier: Programming Language :: Python :: 3.7
Classifier: Programming Language :: Python :: 3.8
Requires-Python: >=3.6
Requires-Dist: numpy
Requires-Dist: scipy
Requires-Dist: astropy
